j_auth_client/__init__.py
j_auth_client/client.py
j_auth_client/exceptions.py
j_auth_client-0.1.0.dist-info/METADATA
j_auth_client-0.1.0.dist-info/WHEEL
j_auth_client-0.1.0.dist-info/licenses/LICENSE
j_auth_client-0.1.0.dist-info/RECORD
