Metadata-Version: 2.4
Name: j-auth-client
Version: 0.1.0
Summary: Auth Client for auth requests
License-File: LICENSE
Requires-Python: >=3.12
Requires-Dist: pyjwt>=2.10.1
Requires-Dist: requests>=2.32.3
